<?xml version="1.0"?>
<annotation>
  <folder>images</folder>
  <filename>101.jpeg</filename>
  <path>../</path>
  <segmented>0</segmented>
  <source>
    <database>Unknown</database>
  </source>
  <size>
    <width>248</width>
    <height>177</height>
    <depth>3</depth>
  </size>
  <object>
    <name>plate</name>
    <pose>Unspecified</pose>
    <truncated>0</truncated>
    <difficult>0</difficult>
    <bndbox>
      <xmin>21</xmin>
      <ymin>56</ymin>
      <xmax>227</xmax>
      <ymax>154</ymax>
    </bndbox>
  </object>
</annotation>