<?xml version="1.0"?>
<annotation>
  <folder>images</folder>
  <filename>171.jpeg</filename>
  <path>../</path>
  <segmented>0</segmented>
  <source>
    <database>Unknown</database>
  </source>
  <size>
    <width>1300</width>
    <height>924</height>
    <depth>3</depth>
  </size>
  <object>
    <name>plate</name>
    <pose>Unspecified</pose>
    <truncated>0</truncated>
    <difficult>0</difficult>
    <bndbox>
      <xmin>396</xmin>
      <ymin>673</ymin>
      <xmax>799</xmax>
      <ymax>783</ymax>
    </bndbox>
  </object>
</annotation>